__init__.py
bunkrr_uploader.py
bunkrr_uploader/__init__.py
bunkrr_uploader/api.py
bunkrr_uploader/bunkrr_uploader.py
bunkrr_uploader/cli.py
bunkrr_uploader/types.py
bunkrr_uploader/util.py
BunkrrUploader-0.10.7.dist-info/LICENSE
BunkrrUploader-0.10.7.dist-info/METADATA
BunkrrUploader-0.10.7.dist-info/WHEEL
BunkrrUploader-0.10.7.dist-info/entry_points.txt
BunkrrUploader-0.10.7.dist-info/top_level.txt
BunkrrUploader-0.10.7.dist-info/RECORD
