Metadata-Version: 2.1
Name: BunkrrUploader
Version: 0.10.7
Summary: Bunkrr uploader supporting parallel uploads
Author-email: Alex Mi <alexmi3.14@gmail.com>
Maintainer-email: Alex Mi <alexmi3.14@gmail.com>
License: MIT License
Project-URL: Homepage, https://github.com/alexmi256/bunkrr-uploader
Project-URL: Repository, https://github.com/alexmi256/bunkrr-uploader.git
Keywords: bunkrr,upload,storage,parallel
Classifier: Development Status :: 4 - Beta
Classifier: Environment :: Console
Classifier: Framework :: aiohttp
Classifier: License :: OSI Approved :: MIT License
Classifier: Intended Audience :: End Users/Desktop
Classifier: Programming Language :: Python :: 3.8
Classifier: Programming Language :: Python :: Implementation
Classifier: Topic :: Internet
Classifier: Topic :: Utilities
Requires-Python: >=3.9
License-File: LICENSE
Requires-Dist: aiohttp
Requires-Dist: tqdm
